opencompass/__init__.py
opencompass/registry.py
opencompass/cli/__init__.py
opencompass/cli/main.py
opencompass/datasets/FinanceIQ.py
opencompass/datasets/GaokaoBench.py
opencompass/datasets/MMLUArabic.py
opencompass/datasets/OpenFinData.py
opencompass/datasets/QuALITY.py
opencompass/datasets/__init__.py
opencompass/datasets/advglue.py
opencompass/datasets/afqmcd.py
opencompass/datasets/anli.py
opencompass/datasets/anthropics_evals.py
opencompass/datasets/apps.py
opencompass/datasets/arc.py
opencompass/datasets/ax.py
opencompass/datasets/base.py
opencompass/datasets/bbh.py
opencompass/datasets/benbench.py
opencompass/datasets/boolq.py
opencompass/datasets/bustum.py
opencompass/datasets/c3.py
opencompass/datasets/cb.py
opencompass/datasets/ceval.py
opencompass/datasets/charm.py
opencompass/datasets/chembench.py
opencompass/datasets/chid.py
opencompass/datasets/cibench.py
opencompass/datasets/circular.py
opencompass/datasets/civilcomments.py
opencompass/datasets/clozeTest_maxmin.py
opencompass/datasets/cluewsc.py
opencompass/datasets/cmb.py
opencompass/datasets/cmmlu.py
opencompass/datasets/cmnli.py
opencompass/datasets/cmrc.py
opencompass/datasets/commonsenseqa.py
opencompass/datasets/commonsenseqa_cn.py
opencompass/datasets/copa.py
opencompass/datasets/crowspairs.py
opencompass/datasets/crowspairs_cn.py
opencompass/datasets/csl.py
opencompass/datasets/custom.py
opencompass/datasets/cvalues.py
opencompass/datasets/drcd.py
opencompass/datasets/drop.py
opencompass/datasets/drop_simple_eval.py
opencompass/datasets/ds1000.py
opencompass/datasets/ds1000_interpreter.py
opencompass/datasets/eprstmt.py
opencompass/datasets/flames.py
opencompass/datasets/flores.py
opencompass/datasets/game24.py
opencompass/datasets/govrepcrs.py
opencompass/datasets/gpqa.py
opencompass/datasets/gsm8k.py
opencompass/datasets/gsm_hard.py
opencompass/datasets/hellaswag.py
opencompass/datasets/huggingface.py
opencompass/datasets/humaneval.py
opencompass/datasets/humaneval_multi.py
opencompass-0.2.6.dist-info/LICENSE
opencompass-0.2.6.dist-info/METADATA
opencompass-0.2.6.dist-info/WHEEL
opencompass-0.2.6.dist-info/entry_points.txt
opencompass-0.2.6.dist-info/top_level.txt
opencompass-0.2.6.dist-info/RECORD
