Metadata-Version: 2.1
Name: opencompass
Version: 0.2.6
Summary: A comprehensive toolkit for large model evaluation
Home-page: https://github.com/open-compass/opencompass
Author: OpenCompass Contributors
Maintainer: OpenCompass Authors
License: Apache License 2.0
Keywords: AI,NLP,in-context learning,large language model,evaluation,benchmark,llm
Platform: UNKNOWN
Classifier: Programming Language :: Python :: 3.8
Classifier: Programming Language :: Python :: 3.9
Classifier: Programming Language :: Python :: 3.10
Classifier: Intended Audience :: Developers
Classifier: Intended Audience :: Education
Classifier: Intended Audience :: Science/Research
Requires-Python: >=3.8.0
Requires-Dist: absl-py
Requires-Dist: accelerate >=0.19.0
Requires-Dist: boto3
Requires-Dist: cn2an
Requires-Dist: cpm-kernels
Requires-Dist: datasets >=2.12.0
Requires-Dist: einops ==0.5.0
Requires-Dist: evaluate >=0.3.0
Requires-Dist: fairscale
Requires-Dist: func-timeout
Requires-Dist: fuzzywuzzy
Requires-Dist: immutabledict
Requires-Dist: jieba
Requires-Dist: json5
Requires-Dist: langdetect
Requires-Dist: ltp
Requires-Dist: mmengine-lite
Requires-Dist: nltk ==3.8
Requires-Dist: numpy <2.0.0,>=1.23.4
Requires-Dist: openai
Requires-Dist: OpenCC
Requires-Dist: opencv-python-headless
Requires-Dist: pandas <2.0.0
Requires-Dist: prettytable
Requires-Dist: protobuf
Requires-Dist: pyext
Requires-Dist: pypinyin
Requires-Dist: python-Levenshtein
Requires-Dist: rank-bm25 ==0.2.2
Requires-Dist: rapidfuzz
Requires-Dist: requests ==2.31.0
Requires-Dist: rich
Requires-Dist: rouge
Requires-Dist: rouge-chinese
Requires-Dist: rouge-score
Requires-Dist: sacrebleu
Requires-Dist: scikit-learn ==1.5.0
Requires-Dist: seaborn
Requires-Dist: sentence-transformers ==2.2.2
Requires-Dist: tabulate
Requires-Dist: tiktoken
Requires-Dist: timeout-decorator
Requires-Dist: tokenizers >=0.13.3
Requires-Dist: torch >=1.13.1
Requires-Dist: tqdm ==4.64.1
Requires-Dist: transformers >=4.29.1
Requires-Dist: typer
